openeo_pg_parser_networkx/__init__.py
openeo_pg_parser_networkx/graph.py
openeo_pg_parser_networkx/pg_schema.py
openeo_pg_parser_networkx/process_registry.py
openeo_pg_parser_networkx/resolving_utils.py
openeo_pg_parser_networkx/utils.py
openeo_pg_parser_networkx-2026.1.2.dist-info/LICENSE
openeo_pg_parser_networkx-2026.1.2.dist-info/METADATA
openeo_pg_parser_networkx-2026.1.2.dist-info/WHEEL
openeo_pg_parser_networkx-2026.1.2.dist-info/RECORD
