Metadata-Version: 2.1
Name: openeo-pg-parser-networkx
Version: 2026.1.2
Summary: Parse OpenEO process graphs from JSON to traversible Python objects.
Home-page: https://github.com/Open-EO/openeo-pg-parser-networkx
License: Apache 2.0
Author: Lukas Weidenholzer
Author-email: lukas.weidenholzer@eodc.eu
Requires-Python: >=3.10,<3.14
Classifier: Development Status :: 4 - Beta
Classifier: Intended Audience :: Developers
Classifier: License :: Other/Proprietary License
Classifier: Programming Language :: Python
Classifier: Programming Language :: Python :: 3
Classifier: Programming Language :: Python :: 3.10
Classifier: Programming Language :: Python :: 3.11
Classifier: Programming Language :: Python :: 3 :: Only
Classifier: Programming Language :: Python :: 3.12
Classifier: Programming Language :: Python :: 3.13
Provides-Extra: plot
Requires-Dist: dask (>=2023.4.0,<2025.2.0)
Requires-Dist: geojson-pydantic (>=1.0.0,<2.0.0)
Requires-Dist: matplotlib (>=3.7.1,<4.0.0) ; extra == "plot"
Requires-Dist: networkx (>=3.0.0)
Requires-Dist: numpy (>=1.20.3,<2.0.0)
Requires-Dist: pendulum (>=3.0.0)
Requires-Dist: pydantic (>=2.4.0,<3.0.0)
Requires-Dist: pyproj (>=3.4.0,<4.0.0)
Requires-Dist: traitlets (<=5.13.0)
Requires-Dist: xarray (>=2022.11.0,<=2025.08.01)
Requires-Dist: yprov4wfs (>=0.0.8)
Project-URL: Repository, https://github.com/Open-EO/openeo-pg-parser-networkx
